MANIFEST.in
setup.cfg
setup.py
riakalchemy/__init__.py
riakalchemy/exceptions.py
riakalchemy/model.py
riakalchemy/types.py
riakalchemy.egg-info/PKG-INFO
riakalchemy.egg-info/SOURCES.txt
riakalchemy.egg-info/dependency_links.txt
riakalchemy.egg-info/requires.txt
riakalchemy.egg-info/top_level.txt