Metadata-Version: 1.0
Name: riakalchemy
Version: 0.1a5
Summary: Object Mapper for Riak
Home-page: https://launchpad.net/riakalchemy
Author: Soren Hansen
Author-email: soren@linux2go.dk
License: LGPL
Platform: UNKNOWN
Classifier: Development Status :: 1 - Planning
Classifier: Intended Audience :: Developers
Classifier: License :: OSI Approved :: GNU Library or Lesser General Public License (LGPL)
Classifier: Operating System :: OS Independent
Classifier: Programming Language :: Python
Classifier: Topic :: Database
Classifier: Topic :: Software Development :: Libraries :: Python Modules
